[
  {
    "modelId": "ancient_palace_01",
    "modelName": "太和殿",
    "modelUrl": "/assets/models/taihe_dian.glb",
    "initConfig": {
      "autoRotate": true,
      "rotationX": 0,
      "rotationY": 0.5,
      "cameraZ": 15
    },
    "markers": [
      {
        "id": "m1",
        "name": "重檐庑殿顶",
        "position": [
          0,
          8,
          0
        ],
        "desc": "太和殿采用重檐庑殿顶，是中国古建筑中等级最高的屋顶形式，仅用于皇宫主殿",
        "linkUrl": "/knowledge/wudian"
      },
      {
        "id": "m2",
        "name": "斗拱",
        "position": [
          2,
          4,
          0
        ],
        "desc": "太和殿使用溜金斗拱，出踩数达九踩，体现了最高等级的建筑规格",
        "linkUrl": "/knowledge/dougong"
      },
      {
        "id": "m3",
        "name": "汉白玉台基",
        "position": [
          0,
          0.5,
          0
        ],
        "desc": "三层汉白玉台基，高8.13米，象征皇权至高无上",
        "linkUrl": "/knowledge/taiji"
      },
      {
        "id": "m4",
        "name": "金龙和玺彩画",
        "position": [
          1,
          5,
          1
        ],
        "desc": "最高等级的彩画形式，以金龙为主要图案",
        "linkUrl": "/knowledge/caihua"
      }
    ],
    "buildingId": "taihe_dian",
    "category": "palace",
    "sourceUrl": "https://www.dpm.org.cn/explore/building/236465.html",
    "sourceName": "故宫博物院官网",
    "confidence": "high",
    "collectedAt": "2026-03-31"
  },
  {
    "modelId": "ancient_bridge_01",
    "modelName": "赵州桥",
    "modelUrl": "/assets/models/zhaozhou_bridge.glb",
    "initConfig": {
      "autoRotate": false,
      "rotationX": 0,
      "rotationY": 0,
      "cameraZ": 20
    },
    "markers": [
      {
        "id": "m1",
        "name": "主拱",
        "position": [
          0,
          5,
          0
        ],
        "desc": "单孔敞肩石拱，跨度37.02米，是世界上现存最早的敞肩拱桥",
        "linkUrl": "/knowledge/qiao"
      },
      {
        "id": "m2",
        "name": "小拱",
        "position": [
          8,
          3,
          0
        ],
        "desc": "两肩各有两个小拱，减轻自重、增加泄洪能力",
        "linkUrl": "/knowledge/qiao"
      },
      {
        "id": "m3",
        "name": "桥面",
        "position": [
          0,
          6,
          0
        ],
        "desc": "桥长64.4米，宽9.6米，可通行车马",
        "linkUrl": "/knowledge/qiao"
      }
    ],
    "buildingId": "zhaozhou_bridge",
    "category": "bridge",
    "sourceUrl": "https://baike.baidu.com/item/中国四大名桥/10263311",
    "sourceName": "百度百科",
    "confidence": "high",
    "collectedAt": "2026-03-31"
  },
  {
    "modelId": "ancient_garden_01",
    "modelName": "拙政园",
    "modelUrl": "/assets/models/zhuozheng_garden.glb",
    "initConfig": {
      "autoRotate": true,
      "rotationX": 0.2,
      "rotationY": 0,
      "cameraZ": 30
    },
    "markers": [
      {
        "id": "m1",
        "name": "水面",
        "position": [
          0,
          0,
          0
        ],
        "desc": "水面占比达3/5，体现明代园林自然风格",
        "linkUrl": "/knowledge/yuanlin"
      },
      {
        "id": "m2",
        "name": "远香堂",
        "position": [
          5,
          2,
          3
        ],
        "desc": "园中主厅，四面环水，夏季荷花飘香",
        "linkUrl": "/knowledge/yuanlin"
      },
      {
        "id": "m3",
        "name": "小飞虹",
        "position": [
          -3,
          1,
          2
        ],
        "desc": "廊桥式建筑，造型优美",
        "linkUrl": "/knowledge/yuanlin"
      }
    ],
    "buildingId": "zhuozheng_garden",
    "category": "garden",
    "sourceUrl": "https://baike.baidu.com/item/拙政园/154079",
    "sourceName": "百度百科",
    "confidence": "high",
    "collectedAt": "2026-03-31"
  }
]
